m6gp/GeneticOperators.py
m6gp/Individual.py
m6gp/M6GP.py
m6gp/MahalanobisDistanceClassifier.py
m6gp/Node.py
m6gp/__init__.py
m6gp-1.1.1.dist-info/METADATA
m6gp-1.1.1.dist-info/WHEEL
m6gp-1.1.1.dist-info/top_level.txt
m6gp-1.1.1.dist-info/RECORD
