Metadata-Version: 2.2
Name: m6gp
Version: 1.1.1
Summary: Python implementation of the M6GP algorithm, a multi-objective genetic programming algorithm for feature engineering
Author-email: João Eduardo Batista <joao.batista@riken.jp>
License: https://opensource.org/licenses/MIT
Project-URL: homepage, https://github.com/jespb/Python-M6GP
Project-URL: repository, https://github.com/jespb/Python-M6GP
Project-URL: documentation, https://github.com/jespb/Python-M6GP
Requires-Python: ~=3.8
